interactions/ext/better_interactions/__init__.py
interactions/ext/better_interactions/callback.py
interactions/ext/better_interactions/components.py
interactions/ext/better_interactions/extension.py
interactions/ext/better_interactions/subcomand.py
better_interactions-2.1.2.dist-info/LICENSE
better_interactions-2.1.2.dist-info/METADATA
better_interactions-2.1.2.dist-info/WHEEL
better_interactions-2.1.2.dist-info/top_level.txt
better_interactions-2.1.2.dist-info/RECORD
