Metadata-Version: 2.1
Name: better-interactions
Version: 2.1.2
Summary: Better interactions for discord-py-interactions
Home-page: https://github.com/Toricane/better-interactions
Author: Toricane
Author-email: prjwl028@gmail.com
License: MIT
Platform: UNKNOWN
Classifier: Programming Language :: Python :: 3
Classifier: Development Status :: 4 - Beta
Classifier: License :: OSI Approved :: MIT License
Classifier: Operating System :: OS Independent
License-File: LICENSE
Requires-Dist: discord-py-interactions (>=4.0.1)
Requires-Dist: interactions-wait-for
